bytedance_primus_torch_io/__init__.py
bytedance_primus_torch_io-0.0.1.dist-info/METADATA
bytedance_primus_torch_io-0.0.1.dist-info/WHEEL
bytedance_primus_torch_io-0.0.1.dist-info/top_level.txt
bytedance_primus_torch_io-0.0.1.dist-info/RECORD
