Metadata-Version: 2.1
Name: bytedance-primus-torch-io
Version: 0.0.1
Summary: A simple package named bytedance_primus_torch_io
Home-page: https://github.com/artifact/bytedance_primus_torch_io.git
Author: artifact
Author-email: artifact@example.com
License: UNKNOWN
Platform: UNKNOWN
Classifier: Programming Language :: Python :: 3
Classifier: License :: OSI Approved :: MIT License
Classifier: Operating System :: OS Independent
